qha-1.1.0.dist-info/METADATA
qha-1.1.0.dist-info/WHEEL
qha-1.1.0.dist-info/entry_points.txt
qha-1.1.0.dist-info/licenses/LICENSE.txt
qha/__init__.py
qha/basic_io/__init__.py
qha/basic_io/input_maker.py
qha/basic_io/out.py
qha/basic_io/read_input.py
qha/calculator.py
qha/cli/__init__.py
qha/cli/converter.py
qha/cli/handler.py
qha/cli/parser.py
qha/cli/plotter.py
qha/cli/runner.py
qha/fitting.py
qha/grid_interpolation.py
qha/multi_configurations/__init__.py
qha/multi_configurations/different_phonon_dos.py
qha/multi_configurations/same_phonon_dos.py
qha/plotting.py
qha/settings.py
qha/single_configuration.py
qha/statmech.py
qha/thermodynamics.py
qha/tools.py
qha/type_aliases.py
qha/unit_conversion.py
qha/v2p.py
qha-1.1.0.dist-info/RECORD
