Metadata-Version: 2.1
Name: qha
Version: 1.1.0
Summary: A powerful tool for quasi-harmonic approximation
Author-Email: Qi Zhang <singularitti@outlook.com>
License: GNU General Public License 3
Requires-Python: >=3.9
Requires-Dist: lazy-property>=0.0.1
Requires-Dist: mpmath>=1
Requires-Dist: pandas>=2
Requires-Dist: scientific-string>=0.1.0
Requires-Dist: scipy>=1
Requires-Dist: text-stream>=0.2.0
Requires-Dist: pyyaml>=6
Requires-Dist: matplotlib>=3
Requires-Dist: numba>=0.58
Requires-Dist: jax>=0.4
